odoo/addons/hr_holidays_natural_period_public/README.rst
odoo/addons/hr_holidays_natural_period_public/__init__.py
odoo/addons/hr_holidays_natural_period_public/__manifest__.py
odoo/addons/hr_holidays_natural_period_public/demo/hr_leave_type_data.xml
odoo/addons/hr_holidays_natural_period_public/i18n/hr_holidays_natural_period_public.pot
odoo/addons/hr_holidays_natural_period_public/i18n/it.po
odoo/addons/hr_holidays_natural_period_public/models/__init__.py
odoo/addons/hr_holidays_natural_period_public/models/resource_calendar.py
odoo/addons/hr_holidays_natural_period_public/readme/CONTRIBUTORS.rst
odoo/addons/hr_holidays_natural_period_public/readme/DESCRIPTION.rst
odoo/addons/hr_holidays_natural_period_public/readme/USAGE.rst
odoo/addons/hr_holidays_natural_period_public/static/description/icon.png
odoo/addons/hr_holidays_natural_period_public/static/description/index.html
odoo/addons/hr_holidays_natural_period_public/tests/__init__.py
odoo/addons/hr_holidays_natural_period_public/tests/test_hr_holidays_natural_period_public.py
odoo_addon_hr_holidays_natural_period_public-16.0.1.1.0.dist-info/METADATA
odoo_addon_hr_holidays_natural_period_public-16.0.1.1.0.dist-info/WHEEL
odoo_addon_hr_holidays_natural_period_public-16.0.1.1.0.dist-info/top_level.txt
odoo_addon_hr_holidays_natural_period_public-16.0.1.1.0.dist-info/RECORD
