Metadata-Version: 2.1
Name: odoo-addon-hr_holidays_natural_period_public
Version: 16.0.1.1.0
Summary: Allow excluding public holidays for natural days holidays
Home-page: https://github.com/OCA/hr-holidays
Author: ForgeFlow, Odoo Community Association (OCA)
Author-email: support@odoo-community.org
License: AGPL-3
Classifier: Programming Language :: Python
Classifier: Framework :: Odoo
Classifier: Framework :: Odoo :: 16.0
Classifier: License :: OSI Approved :: GNU Affero General Public License v3
Requires-Python: >=3.10
Requires-Dist: odoo-addon-hr-holidays-natural-period<16.1dev,>=16.0dev
Requires-Dist: odoo-addon-hr-holidays-public<16.1dev,>=16.0dev
Requires-Dist: odoo<16.1dev,>=16.0a
